sql_model_cleaner/__init__.py
sql_model_cleaner/main.py
cbcsncleaner-0.1.5.dist-info/METADATA
cbcsncleaner-0.1.5.dist-info/WHEEL
cbcsncleaner-0.1.5.dist-info/entry_points.txt
cbcsncleaner-0.1.5.dist-info/top_level.txt
cbcsncleaner-0.1.5.dist-info/RECORD
